{
	"info": {
		"_postman_id": "12b0dc32-d4f9-4c44-a90d-a9161c7b66d4",
		"name": "Ceragon",
		"schema": "https://schema.getpostman.com/json/collection/v2.1.0/collection.json",
		"_exporter_id": "14008876"
	},
	"item": [
		{
			"name": "autores",
			"item": [
				{
					"name": "http://127.0.0.1:8000/api/autores/",
					"request": {
						"method": "GET",
						"header": []
					},
					"response": []
				},
				{
					"name": "http://127.0.0.1:8000/api/libros/1",
					"request": {
						"method": "GET",
						"header": []
					},
					"response": []
				},
				{
					"name": "create",
					"request": {
						"method": "GET",
						"header": []
					},
					"response": []
				},
				{
					"name": "delete",
					"request": {
						"method": "GET",
						"header": []
					},
					"response": []
				},
				{
					"name": "PUT",
					"request": {
						"method": "GET",
						"header": []
					},
					"response": []
				}
			]
		},
		{
			"name": "Libros",
			"item": [
				{
					"name": "http://127.0.0.1:8000/api/libros/",
					"request": {
						"method": "GET",
						"header": []
					},
					"response": []
				},
				{
					"name": "http://127.0.0.1:8000/api/libros/1",
					"request": {
						"method": "GET",
						"header": []
					},
					"response": []
				},
				{
					"name": "create",
					"request": {
						"method": "GET",
						"header": []
					},
					"response": []
				},
				{
					"name": "delete",
					"request": {
						"method": "GET",
						"header": []
					},
					"response": []
				},
				{
					"name": "PUT",
					"request": {
						"method": "GET",
						"header": []
					},
					"response": []
				}
			]
		},
		{
			"name": "Filtros/Aggregate",
			"item": [
				{
					"name": "Filtros complejos",
					"request": {
						"method": "GET",
						"header": []
					},
					"response": []
				}
			]
		},
		{
			"name": "Annotate",
			"item": [
				{
					"name": "estadistadiscas",
					"request": {
						"method": "GET",
						"header": []
					},
					"response": []
				}
			]
		}
	]
}